[
    {
        "name": "websites.edit",
        "scope": "functions",
        "function": "websites",
        "description": "Allow creating and editing websites",
        "type": "boolean",
        "dvalue": "true"
    },
    {
        "name": "websites.delete",
        "scope": "functions",
        "function": "websites",
        "description": "Allow deleting websites",
        "type": "boolean",
        "dvalue": "true"
    },
	{
        "name": "items.create",
        "scope": "functions",
        "function": "items",
        "description": "Allow creating new items",
        "type": "boolean",
        "dvalue": "true"
    },
	{
        "name": "items.edit",
        "scope": "functions",
        "function": "items",
        "description": "Allow editing items",
        "type": "boolean",
        "dvalue": "true"
    },
	{
        "name": "items.delete",
        "scope": "functions",
        "function": "items",
        "description": "Allow deleting items",
        "type": "boolean",
        "dvalue": "true"
    },
	{
        "name": "items.publish",
        "scope": "functions",
        "function": "items",
        "description": "Allow publishing items",
        "type": "boolean",
        "dvalue": "true"
    },
    {
        "name": "files.upload",
        "scope": "functions",
        "function": "files",
        "description": "Allow uploading files",
        "type": "boolean",
        "dvalue": "true"
    },
	{
        "name": "files.delete",
        "scope": "functions",
        "function": "files",
        "description": "Allow deleting files",
        "type": "boolean",
        "dvalue": "true"
    }
]